DenoEngine/__init__.py
DenoEngine/core.py
DenoEngine/input.py
DenoEngine/objects.py
denoenginev1-0.1.0.dist-info/METADATA
denoenginev1-0.1.0.dist-info/WHEEL
denoenginev1-0.1.0.dist-info/top_level.txt
denoenginev1-0.1.0.dist-info/RECORD
