Metadata-Version: 2.4
Name: denoengineV1
Version: 0.1.0
Summary: Basit bir 3D oyun motoru (OpenGL + GLFW)
Author: DenoTUBE
Requires-Python: >=3.8
Requires-Dist: PyOpenGL
Requires-Dist: glfw
Dynamic: author
Dynamic: requires-dist
Dynamic: requires-python
Dynamic: summary
